{
  "language": [
    {
      "name": "Java",
      "important": 5,
      "usage": 5,
      "current": 5,
      "future": 5,
      "description": "--------"
    }
  ],
  "tools": [
    {
      "name": "Linux",
      "important": 1,
      "usage": 1,
      "current": 2,
      "future": 2,
      "description": "--------"
    }
  ],
  "others": [
    {
      "name": "Agile",
      "important": 3,
      "usage": 5,
      "current": 3,
      "future": 3,
      "description": "--------"
    }
  ],
  "frameworks": [
    {
      "name": "Node.js",
      "important": 3,
      "usage": 5,
      "current": 3,
      "future": 5,
      "description": "--------"
    }
  ]
}
